odoo/addons/ssi_task_type/README.rst
odoo/addons/ssi_task_type/__init__.py
odoo/addons/ssi_task_type/__manifest__.py
odoo/addons/ssi_task_type/i18n/ssi_task_type.pot
odoo/addons/ssi_task_type/models/__init__.py
odoo/addons/ssi_task_type/models/project_task.py
odoo/addons/ssi_task_type/models/task_type.py
odoo/addons/ssi_task_type/models/task_type_category.py
odoo/addons/ssi_task_type/models/task_type_instruction.py
odoo/addons/ssi_task_type/models/task_type_sucessor.py
odoo/addons/ssi_task_type/security/ir.model.access.csv
odoo/addons/ssi_task_type/security/res_group_data.xml
odoo/addons/ssi_task_type/static/description/icon.png
odoo/addons/ssi_task_type/views/project_task_views.xml
odoo/addons/ssi_task_type/views/task_type_category_views.xml
odoo/addons/ssi_task_type/views/task_type_views.xml
odoo/addons/ssi_task_type/wizards/__init__.py
odoo/addons/ssi_task_type/wizards/create_sucessor_task.py
odoo/addons/ssi_task_type/wizards/create_sucessor_task.xml
odoo14_addon_ssi_task_type-14.0.1.11.0.dist-info/METADATA
odoo14_addon_ssi_task_type-14.0.1.11.0.dist-info/WHEEL
odoo14_addon_ssi_task_type-14.0.1.11.0.dist-info/top_level.txt
odoo14_addon_ssi_task_type-14.0.1.11.0.dist-info/RECORD
